asyncprawcore/__init__.py
asyncprawcore/auth.py
asyncprawcore/codes.py
asyncprawcore/const.py
asyncprawcore/exceptions.py
asyncprawcore/rate_limit.py
asyncprawcore/requestor.py
asyncprawcore/sessions.py
asyncprawcore/util.py
asyncprawcore-3.0.2.dist-info/licenses/LICENSE.txt
asyncprawcore-3.0.2.dist-info/WHEEL
asyncprawcore-3.0.2.dist-info/METADATA
asyncprawcore-3.0.2.dist-info/RECORD
