Metadata-Version: 2.4
Name: asyncprawcore
Version: 3.0.2
Summary: Low-level asynchronous communication layer for Async PRAW 7+.
Keywords: praw,reddit,api,async,asynchronous,asyncpraw
Author-email: Joel Payne <lilspazjoekp@gmail.com>
Maintainer-email: Joel Payne <lilspazjoekp@gmail.com>
Requires-Python: >=3.9
Classifier: Development Status :: 5 - Production/Stable
Classifier: Intended Audience :: Developers
Classifier: License :: OSI Approved :: BSD License
Classifier: Operating System :: OS Independent
Classifier: Natural Language :: English
Classifier: Programming Language :: Python
Classifier: Programming Language :: Python :: 3
Classifier: Programming Language :: Python :: 3.9
Classifier: Programming Language :: Python :: 3.10
Classifier: Programming Language :: Python :: 3.11
Classifier: Programming Language :: Python :: 3.12
Classifier: Programming Language :: Python :: 3.13
License-File: LICENSE.txt
Requires-Dist: aiohttp <4
Requires-Dist: yarl
Project-URL: Issue Tracker, https://github.com/praw-dev/asyncprawcore/issues
Project-URL: Source Code, https://github.com/praw-dev/asyncprawcore
